MANIFEST.in
README.md
setup.py
bin/iprange
ipoperate/__init__.py
ipoperate/ipoperate.py
ipoperate.egg-info/PKG-INFO
ipoperate.egg-info/SOURCES.txt
ipoperate.egg-info/dependency_links.txt
ipoperate.egg-info/top_level.txt