Metadata-Version: 1.1
Name: ipoperate
Version: 1.1
Summary: magic functions to operate ips and nets
Home-page: http://www.xdays.info
Author: Alair Zhang (xdays)
Author-email: easedays@gmail.com
License: License :: OSI Approved :: MIT License
Keywords: ipoperate,ip2net,nets2net,ip2bin
Platform: Platform Independent
Classifier: Development Status :: 5 - Production/Stable
Classifier: Intended Audience :: Developers
Classifier: License :: OSI Approved :: MIT License
Classifier: Operating System :: OS Independent
Classifier: Programming Language :: Python
Classifier: Programming Language :: Python :: 2
Classifier: Programming Language :: Python :: 2.6
Classifier: Programming Language :: Python :: 2.7
